{
  "parent": "minecraft:recipes/root",
  "criteria": {
    "has_any_log": {
      "conditions": {
        "items": [
          {
            "items": "#minecraft:logs"
          }
        ]
      },
      "trigger": "minecraft:inventory_changed"
    },
    "has_the_recipe": {
      "conditions": {
        "recipe": "millenaire:cross_timber_frame"
      },
      "trigger": "minecraft:recipe_unlocked"
    }
  },
  "requirements": [
    [
      "has_the_recipe",
      "has_any_log"
    ]
  ],
  "rewards": {
    "recipes": [
      "millenaire:cross_timber_frame"
    ]
  }
}